ataims/__init__.py
ataims/__main__.py
ataims/common_util.py
ataims/conf.py
ataims/exceptions.py
ataims/mathlib.py
ataims/model.py
ataims/output.py
ataims/output_aims.py
ataims/output_exciting.py
ataims/parser.py
ataims/structure.py
ataims/util.py
ataims/version.py
ataims-0.1.1.dist-info/LICENSE.md
ataims-0.1.1.dist-info/METADATA
ataims-0.1.1.dist-info/WHEEL
ataims-0.1.1.dist-info/top_level.txt
ataims-0.1.1.dist-info/RECORD
