Metadata-Version: 2.1
Name: ataims
Version: 0.1.1
Summary: A package for parsing AIMS output files
Author-email: Steven Anderson <steven@atomictessellator.com>, Alain Richardt <alain@atomictessellator.com>
Project-URL: Homepage, https://github.com/AtomicTessellator/at-aims
Requires-Python: >=3.10
License-File: LICENSE.md
Requires-Dist: annotated-types>=0.7.0
Requires-Dist: numpy>=1.26.2
Requires-Dist: pandas>=2.2.3
Requires-Dist: pydantic>=2.9.2
Requires-Dist: pydantic-core>=2.23.4
Requires-Dist: python-dateutil>=2.9.0
Requires-Dist: pytz>=2024.2
Requires-Dist: six>=1.16.0
Requires-Dist: typing-extensions>=4.12.2
Requires-Dist: tzdata>=2024.2
Provides-Extra: dev
Requires-Dist: pytest>=6.0; extra == "dev"
